aggregator.py
escapeaggregator-0.1.2.dist-info/LICENSE
escapeaggregator-0.1.2.dist-info/METADATA
escapeaggregator-0.1.2.dist-info/WHEEL
escapeaggregator-0.1.2.dist-info/top_level.txt
escapeaggregator-0.1.2.dist-info/RECORD
